{"birth":{"x":429,"y":243,"width":200,"height":200},"mob":[{"id":40,"x":1685,"y":266,"width":180,"height":180,"level":0,"kindId":7701,"name":"鸡腿","num":4,"refreshTime":3000}],"transport":[{"id":20,"x":111,"y":361,"width":100,"height":60,"kindId":20001,"atArea":3001,"targetArea":3002,"name":"云梦乡"}],"npc":[{"id":4,"x":843,"y":223,"width":130,"height":151,"kindId":30016,"name":"驿站"}],"collisions":{"0":[[23,16]],"1":[[23,16]],"2":[[0,1],[23,16]],"3":[[0,1],[23,16]],"4":[[0,1],[23,16]],"5":[[0,1],[23,16]],"6":[[0,2],[23,16]],"7":[[0,2],[23,16]],"8":[[0,3],[22,17]],"9":[[0,3],[22,17]],"10":[[0,3],[22,17]],"11":[[0,3],[22,17]],"12":[[0,3],[22,17]],"13":[[0,3],[22,17]],"14":[[0,3],[22,17]],"15":[[0,2],[22,17]],"16":[[0,2],[23,16]],"17":[[0,2],[23,16]],"18":[[0,1],[24,15]],"19":[[0,1],[24,15]],"20":[[0,1],[24,15]],"21":[[24,15]],"22":[[24,15]],"23":[[24,15]],"24":[[24,15]],"25":[[23,16]],"26":[[22,17]],"27":[[21,18]],"28":[[21,18]],"29":[[21,18]],"30":[[21,18]],"31":[[14,3],[22,17]],"32":[[14,3],[22,17]],"33":[[13,6],[22,17]],"34":[[13,6],[22,17]],"35":[[13,8],[22,17]],"36":[[16,5],[22,17]],"37":[[17,22]],"38":[[17,22]],"39":[[17,22]],"40":[[17,22]],"41":[[15,24]],"42":[[15,24]],"43":[[15,24]],"44":[[15,24]],"45":[[15,24]],"46":[[15,24]],"47":[[16,23]],"48":[[16,23]],"49":[[16,23]],"50":[[16,23]],"51":[[16,23]],"52":[[16,2],[20,19]],"53":[[16,2],[20,19]],"54":[[16,2],[20,19]],"55":[[16,2],[20,19]],"56":[[16,2],[20,19]],"57":[[16,2],[20,19]],"58":[[17,1],[20,19]],"59":[[17,1],[20,19]],"60":[[20,19]],"61":[[20,19]],"62":[[20,19]],"63":[[20,19]],"64":[[20,19]],"65":[[20,19]],"66":[[17,1],[20,19]],"67":[[17,1],[20,19]],"68":[[17,2],[20,19]],"69":[[17,2],[20,19]],"70":[[17,2],[20,19]],"71":[[17,22]],"72":[[18,21]],"73":[[18,21]],"74":[[18,21]],"75":[[18,21]],"76":[[19,20]],"77":[[19,20]],"78":[[19,20]],"79":[[0,2],[19,20]],"80":[[0,3],[19,20]],"81":[[0,3],[19,20]],"82":[[0,3],[19,20]],"83":[[0,4],[19,20]],"84":[[0,4],[19,20]],"85":[[0,5],[19,20]],"86":[[0,5],[19,20]],"87":[[0,5],[19,20]],"88":[[0,5],[9,1],[19,20]],"89":[[0,5],[9,1],[19,20]],"90":[[0,5],[9,2],[19,20]],"91":[[0,5],[9,2],[19,20]],"92":[[0,4],[8,4],[19,20]],"93":[[0,4],[7,5],[18,21]],"94":[[0,4],[7,7],[18,21]],"95":[[0,3],[6,33]],"96":[[0,4],[6,33]],"97":[[0,4],[6,33]],"98":[[0,4],[6,33]],"99":[[0,5],[6,33]],"100":[[0,39]],"101":[[0,39]],"102":[[0,39]]},"marks":{"0":[[6,8]],"1":[[6,8]],"2":[[6,8]],"3":[[1,12]],"4":[[1,12]],"5":[[1,12]],"6":[[2,11]],"7":[[2,10]],"8":[[3,6]],"9":[[3,4]],"10":[[3,3]],"11":[[3,3]],"12":[[3,3]],"82":[[5,1]],"83":[[4,2],[10,2]],"84":[[4,1],[9,2]],"85":[[8,3]],"86":[[5,5]],"87":[[5,4]],"88":[[5,2]]}}